metal_sdk/__init__.py
metal_sdk/metal.py
metal_sdk/metal_async.py
metal_sdk/motorhead.py
metal_sdk/motorhead_async.py
metal_sdk/typings.py
metal_sdk-2.5.0.dist-info/METADATA
metal_sdk-2.5.0.dist-info/WHEEL
metal_sdk-2.5.0.dist-info/licenses/LICENSE
metal_sdk-2.5.0.dist-info/RECORD
