Metadata-Version: 2.1
Name: metal_sdk
Version: 2.5.0
Summary: SDK for getmetal.io
Project-URL: Github, https://github.com/getmetal/metal-python
Author-email: Metal Technologies Inc <james@getmetal.io>
License-File: LICENSE
Classifier: License :: OSI Approved :: Apache Software License
Classifier: Programming Language :: Python :: 3
Requires-Python: >=3.7
Requires-Dist: httpx
Requires-Dist: typing-extensions
